odoo8_addon_pos_order_to_sale_order-8.0.2.0.0-py2.7-nspkg.pth
odoo8_addon_pos_order_to_sale_order-8.0.2.0.0.dist-info/DESCRIPTION.rst
odoo8_addon_pos_order_to_sale_order-8.0.2.0.0.dist-info/METADATA
odoo8_addon_pos_order_to_sale_order-8.0.2.0.0.dist-info/RECORD
odoo8_addon_pos_order_to_sale_order-8.0.2.0.0.dist-info/WHEEL
odoo8_addon_pos_order_to_sale_order-8.0.2.0.0.dist-info/metadata.json
odoo8_addon_pos_order_to_sale_order-8.0.2.0.0.dist-info/namespace_packages.txt
odoo8_addon_pos_order_to_sale_order-8.0.2.0.0.dist-info/top_level.txt
odoo_addons/pos_order_to_sale_order/README.rst
odoo_addons/pos_order_to_sale_order/__init__.py
odoo_addons/pos_order_to_sale_order/__openerp__.py
odoo_addons/pos_order_to_sale_order/demo/product_template.xml
odoo_addons/pos_order_to_sale_order/demo/res_groups.xml
odoo_addons/pos_order_to_sale_order/demo/sale_order.xml
odoo_addons/pos_order_to_sale_order/demo/stock_picking_type.xml
odoo_addons/pos_order_to_sale_order/i18n/fr.po
odoo_addons/pos_order_to_sale_order/models/__init__.py
odoo_addons/pos_order_to_sale_order/models/pos_config.py
odoo_addons/pos_order_to_sale_order/models/sale_order.py
odoo_addons/pos_order_to_sale_order/static/description/icon.png
odoo_addons/pos_order_to_sale_order/static/description/pos_config_form.png
odoo_addons/pos_order_to_sale_order/static/description/pos_create_picking_confirm.png
odoo_addons/pos_order_to_sale_order/static/description/pos_create_picking_option_1.png
odoo_addons/pos_order_to_sale_order/static/description/pos_create_picking_option_2.png
odoo_addons/pos_order_to_sale_order/static/description/pos_create_picking_option_3.png
odoo_addons/pos_order_to_sale_order/static/src/js/pos_order_to_sale_order.js
odoo_addons/pos_order_to_sale_order/static/src/xml/pos_order_to_sale_order.xml
odoo_addons/pos_order_to_sale_order/views/pos_order_to_sale_order.xml
odoo_addons/pos_order_to_sale_order/views/view_pos_config.xml
