Metadata-Version: 2.0
Name: odoo8-addon-pos-order-to-sale-order
Version: 8.0.2.0.0
Summary: PoS Order To Sale Order
Home-page: https://odoo-community.org/
Author: GRAP,Odoo Community Association (OCA)
Author-email: support@odoo-community.org
License: AGPL-3
Platform: UNKNOWN
Classifier: Programming Language :: Python
Classifier: Framework :: Odoo
Classifier: License :: OSI Approved :: GNU Affero General Public License v3
Requires-Python: ~=2.7
Requires-Dist: odoo (<9.0a,>=8.0a)
